navigation_utilities/__init__.py
navigation_utilities/coordinate.py
navigation_utilities/gngga.py
navigation_utilities/nmea.py
navigation_utilities/oxts.py
navigation_utilities/utils/__init__.py
navigation_utilities/utils/time.py
navigation_utilities-0.2.2.dist-info/LICENSE
navigation_utilities-0.2.2.dist-info/METADATA
navigation_utilities-0.2.2.dist-info/WHEEL
navigation_utilities-0.2.2.dist-info/top_level.txt
navigation_utilities-0.2.2.dist-info/RECORD
