Metadata-Version: 2.1
Name: navigation-utilities
Version: 0.2.2
Summary: Collection of utilities for driverless navigation systems and gnss tools
Author-email: Pablo Dorrio Vazquez <pablo.dorrio.vazquez@gmail.com>
Project-URL: Homepage, https://github.com/pablodorrio/navigation-utilities
Project-URL: Bug Tracker, https://github.com/pablodorrio/navigation-utilities/issues
Classifier: Programming Language :: Python :: 3
Classifier: License :: OSI Approved :: MIT License
Classifier: Operating System :: OS Independent
Requires-Python: >=3.8
License-File: LICENSE
Requires-Dist: numpy (>=1.24.1)
